hitbtcapi/__init__.py
hitbtcapi/constants.py
hitbtcapi/hitbtc.py
hitbtcapi/hitbtcClient.py
hitbtc_api_brunohenz-0.0.5.dist-info/LICENSE
hitbtc_api_brunohenz-0.0.5.dist-info/METADATA
hitbtc_api_brunohenz-0.0.5.dist-info/WHEEL
hitbtc_api_brunohenz-0.0.5.dist-info/top_level.txt
hitbtc_api_brunohenz-0.0.5.dist-info/RECORD
